acme_rofl/__init__.py
acme_rofl-0.0.3.data/data/share/acme-rofl/README.md
acme_rofl-0.0.3.data/data/share/acme-rofl/acme-rofl.service
acme_rofl-0.0.3.dist-info/LICENSE
acme_rofl-0.0.3.dist-info/METADATA
acme_rofl-0.0.3.dist-info/WHEEL
acme_rofl-0.0.3.dist-info/entry_points.txt
acme_rofl-0.0.3.dist-info/top_level.txt
acme_rofl-0.0.3.dist-info/RECORD
