Metadata-Version: 2.1
Name: acme-rofl
Version: 0.0.3
Summary: Respond to ACME challenges, forward all other requests to port 443
Home-page: https://github.com/jvasile/acme-rofl
Author: James Vasile
Author-email: james@opentechstrategies.com
License: UNKNOWN
Platform: UNKNOWN
Classifier: Programming Language :: Python :: 3
Classifier: License :: OSI Approved :: GNU Affero General Public License v3 or later (AGPLv3+)
Classifier: Development Status :: 4 - Beta
Classifier: Framework :: Twisted
Classifier: Operating System :: POSIX
Requires-Python: >=3.4
